Workbook

Sheet WBS - 85 Tasks Backlog
A1: DỰ ÁN WEBCHICKEN E-COMMERCE — BẢN PHÂN RÃ CÔNG VIỆC (WBS 85 TASKS BACKLOG)
A2: MÃ TASK | B2: GIAI ĐOẠN (PHASE) | C2: PHÂN HỆ / MODULE | D2: TÊN CÔNG VIỆC (TASK NAME) | E2: LOẠI | F2: ƯU TIÊN | G2: YÊU CẦU CỤ THỂ (ACCEPTANCE CRITERIA) | H2: HƯỚNG LÀM KỸ THUẬT (IMPLEMENTATION GUIDELINE) | I2: TIẾN ĐỘ (CHECKBOX) | J2: TRẠNG THÁI
A3: TASK-01 | B3: Giai đoạn 1: Nền tảng Hạ tầng & Core Engine | C3: Web & Filter Chain | D3: Cấu hình toàn diện web.xml và đăng ký Filter Chain | E3: Backend | F3: P0 | G3: Khai báo và ánh xạ thứ tự cố định 9 Filters trong web.xml cho /* hoặc /api/v1/*; tắt cơ chế tự tạo session của Tomcat. | H3: Cấu hình <filter> và <filter-mapping> theo thứ tự: RequestId -> GlobalException -> CharacterEncoding -> Cors -> SecurityHeaders -> RateLimit -> Authentication -> CsrfGuard -> Authorization. Thiết lập session tracking COOKIE và không dùng HttpSession. | I3: ✓ ĐÃ XONG | J3: =IF(I3="✓ ĐÃ XONG","Hoàn thành","Đang chờ")
A4: TASK-02 | B4: Giai đoạn 1: Nền tảng Hạ tầng & Core Engine | C4: Web & Filter Chain | D4: Hoàn thiện RequestIdFilter và Logging MDC | E4: Backend | F4: P0 | G4: Mọi request đi vào hệ thống phải có X-Request-Id duy nhất để truy vết toàn trình qua log. | H4: Đọc header X-Request-Id hoặc sinh UUID mới. Gán vào org.slf4j.MDC('requestId') và ghi header trả về client. Đảm bảo xóa MDC trong khối finally. | I4: ✓ ĐÃ XONG | J4: =IF(I4="✓ ĐÃ XONG","Hoàn thành","Đang chờ")
A5: TASK-03 | B5: Giai đoạn 1: Nền tảng Hạ tầng & Core Engine | C5: Web & Filter Chain | D5: Hoàn thiện CharacterEncodingFilter và SecurityHeadersFilter | E5: Backend | F5: P0 | G5: Ép kiểu ký tự tiếng Việt chuẩn UTF-8 và thiết lập các HTTP Security Headers tiêu chuẩn OWASP. | H5: Ép UTF-8 cho request/response. SecurityHeadersFilter thêm: X-Content-Type-Options: nosniff, X-Frame-Options: DENY, HSTS (max-age 1 năm), CSP cơ bản. | I5: ✓ ĐÃ XONG | J5: =IF(I5="✓ ĐÃ XONG","Hoàn thành","Đang chờ")
A6: TASK-04 | B6: Giai đoạn 1: Nền tảng Hạ tầng & Core Engine | C6: Web & Filter Chain | D6: Hoàn thiện CorsFilter cho môi trường Dev và Production | E6: Backend | F6: P0 | G6: Xử lý preflight request OPTIONS và bảo vệ tài nguyên khi gọi chéo origin từ frontend Vite. | H6: Đọc allowed origins từ env. Trả Access-Control-Allow-Origin, Methods, Headers, Allow-Credentials: true. Nếu request là OPTIONS, trả 200 OK ngay lập tức. | I6: ✓ ĐÃ XONG | J6: =IF(I6="✓ ĐÃ XONG","Hoàn thành","Đang chờ")
A7: TASK-05 | B7: Giai đoạn 1: Nền tảng Hạ tầng & Core Engine | C7: Web & Filter Chain | D7: Hoàn thiện GlobalExceptionFilter và chuẩn hóa phản hồi lỗi | E7: Backend | F7: P0 | G7: Không để lộ stack trace ra client; chuyển toàn bộ exception thành format JSON ApiError chuẩn. | H7: Bọc doFilter trong try-catch. Bắt AppException ánh xạ ErrorCode sang HTTP status tương ứng (400, 401, 403, 404, 409). Bắt Throwable log lỗi kèm requestId và trả 500 INTERNAL_SERVER_ERROR. | I7: ✓ ĐÃ XONG | J7: =IF(I7="✓ ĐÃ XONG","Hoàn thành","Đang chờ")
A8: TASK-06 | B8: Giai đoạn 1: Nền tảng Hạ tầng & Core Engine | C8: Web Base | D8: Triển khai BaseApiServlet và Response Utilities | E8: Backend | F8: P0 | G8: Chuẩn hóa lớp cơ sở cho toàn bộ Servlet để đọc request body JSON và trả response chuẩn ApiError/ApiResponse. | H8: Viết generic method readBody(req, Class<T>), ok(resp, data), created(resp, data), badRequest(resp, code, msg). Cung cấp helper lấy service instance từ ServletContext an toàn. | I8: ✓ ĐÃ XONG | J8: =IF(I8="✓ ĐÃ XONG","Hoàn thành","Đang chờ")
A9: TASK-07 | B9: Giai đoạn 1: Nền tảng Hạ tầng & Core Engine | C9: Web & Filter Chain | D9: Hoàn thiện RateLimitFilter (Token Bucket Algorithm) | E9: Backend | F9: P1 | G9: Chống brute-force và spam request vào các endpoint nhạy cảm (auth, checkout). | H9: Xây dựng Token Bucket in-memory dựa trên ConcurrentHashMap theo IP. Giới hạn 10 req/s cho auth. Trả mã 429 Too Many Requests kèm header Retry-After khi vượt ngưỡng. | I9: ✓ ĐÃ XONG | J9: =IF(I9="✓ ĐÃ XONG","Hoàn thành","Đang chờ")
A10: TASK-08 | B10: Giai đoạn 1: Nền tảng Hạ tầng & Core Engine | C10: Security & Auth | D10: Xây dựng JwtProvider và Quản lý Secret Key | E10: Backend | F10: P0 | G10: Sinh và kiểm tra tính hợp lệ của JWT access token bằng thư viện JJWT. | H10: Tạo JwtProvider đọc JWT_SECRET (>= 256-bit) từ env. Cung cấp generateAccessToken(user, roles) hạn 15-30 phút, validateToken(token), và getClaims(token). | I10: ✓ ĐÃ XONG | J10: =IF(I10="✓ ĐÃ XONG","Hoàn thành","Đang chờ")
A11: TASK-09 | B11: Giai đoạn 1: Nền tảng Hạ tầng & Core Engine | C11: Security & Auth | D11: Hoàn thiện AuthenticationFilter và AuthorizationFilter | E11: Backend | F11: P0 | G11: Xác thực Bearer token và kiểm tra phân quyền RBAC (Role-Based Access Control). | H11: AuthenticationFilter: Đọc Bearer token, validate qua JwtProvider, inject AuthenticatedUser vào request attribute. AuthorizationFilter: So khớp route (/admin/*, /seller/*) với roles của user, chặn 403 nếu không đủ quyền. | I11: ✓ ĐÃ XONG | J11: =IF(I11="✓ ĐÃ XONG","Hoàn thành","Đang chờ")
A12: TASK-10 | B12: Giai đoạn 1: Nền tảng Hạ tầng & Core Engine | C12: Database & Migration | D12: Tích hợp Flyway Migration vào AppBootstrapListener | E12: Database | F12: P0 | G12: Tự động migrate schema MySQL khi Tomcat khởi động trước khi tạo JPA EntityManagerFactory. | H12: Trong AppBootstrapListener.contextInitialized(), nạp cấu hình DB từ env, gọi Flyway.configure().dataSource(...).load().migrate(). Bắt exception và log rõ nếu migrate lỗi. | I12: ✓ ĐÃ XONG | J12: =IF(I12="✓ ĐÃ XONG","Hoàn thành","Đang chờ")
A13: TASK-11 | B13: Giai đoạn 1: Nền tảng Hạ tầng & Core Engine | C13: Bootstrap & DI | D13: Mở rộng CompositionRoot cho toàn bộ 11 Modules | E13: Backend | F13: P0 | G13: Khởi tạo và tiêm phụ thuộc thủ công qua constructor cho tất cả DAO và Service của dự án. | H13: Trong CompositionRoot.java: Khởi tạo tất cả DAO (truyền EMF), khởi tạo các ServiceImpl (truyền DAO tương ứng), gán vào ServletContext với key chuẩn để Servlet truy xuất. | I13: ✓ ĐÃ XONG | J13: =IF(I13="✓ ĐÃ XONG","Hoàn thành","Đang chờ")
A14: TASK-12 | B14: Giai đoạn 1: Nền tảng Hạ tầng & Core Engine | C14: Event Infrastructure | D14: Xây dựng EventBus nội bộ cho Domain Events | E14: Backend | F14: P1 | G14: Giao tiếp bất đồng bộ giữa các module nội bộ mà không làm nghẽn luồng xử lý chính. | H14: Tạo SimpleEventBus sử dụng ThreadPoolExecutor có tên luồng và giới hạn worker. Đăng ký listener và phát event (OrderPlaced, PaymentCompleted). Shutdown thread pool an toàn trong contextDestroyed. | I14: ✓ ĐÃ XONG | J14: =IF(I14="✓ ĐÃ XONG","Hoàn thành","Đang chờ")
... A87: TASK-85 | B87: Giai đoạn 6: Containerization, CI/CD & Go-Live | C87: DevOps & Ops | D87: Lập Kế hoạch Chuyển dịch Hệ thống & Nghiệm thu Go-Live (Cutover Checklist) | E87: Ops | F87: P0 | G87: Quy trình chuẩn mực từng bước để đưa hệ thống vào vận hành thực tế không gián đoạn. | H87: Soạn thảo docs/dev-guides/GO_LIVE_CHECKLIST.md: Đổi mật khẩu mặc định, cài SSL Let's Encrypt, nạp API Key cổng thanh toán production, chạy Flyway migration prod, runbook backup/rollback. | I87: ☐ CHƯA XONG | J87: =IF(I87="✓ ĐÃ XONG","Hoàn thành","Đang chờ")

Sheet Thống kê Tiến độ (Dashboard)
B2: BẢNG ĐIỀU KHIỂN TIẾN ĐỘ THỰC HIỆN DỰ ÁN WEBCHICKEN
B4: Tổng số công việc (Total Tasks): | C4: 85
B5: Số công việc đã hoàn thành (Done): | C5: =COUNTIF('WBS - 85 Tasks Backlog'!I3:I87, "✓ ĐÃ XONG")
B6: Số công việc còn lại (Pending): | C6: =C4-C5
B7: Tỷ lệ hoàn thành toàn dự án (%): | C7: =C5/C4
B10: TIẾN ĐỘ THEO TỪNG GIAI ĐOẠN (PHASE BREAKDOWN)
B11: Giai đoạn | C11: Tổng Tasks | D11: Đã xong | E11: Còn lại | F11: Tỷ lệ %
B12: Giai đoạn 1: Nền tảng Hạ tầng & Core Engine | C12: 15 | D12: =COUNTIF('WBS - 85 Tasks Backlog'!I3:I17, "✓ ĐÃ XONG") | E12: =C12-D12 | F12: =D12/C12
B13: Giai đoạn 2: Nghiệp vụ Lõi - Phase 1: Identity, Store & Catalog | C13: 20 | D13: =COUNTIF('WBS - 85 Tasks Backlog'!I18:I37, "✓ ĐÃ XONG") | E13: =C13-D13 | F13: =D13/C13
B14: Giai đoạn 3: Nghiệp vụ Giao dịch - Phase 2: Inventory, Cart, Promo, Order & Payment | C14: 20 | D14: =COUNTIF('WBS - 85 Tasks Backlog'!I38:I57, "✓ ĐÃ XONG") | E14: =C14-D14 | F14: =D14/C14
B15: Giai đoạn 4: Hậu mãi, Seller Portal & Backoffice | C15: 15 | D15: =COUNTIF('WBS - 85 Tasks Backlog'!I58:I72, "✓ ĐÃ XONG") | E15: =C15-D15 | F15: =D15/C15
B16: Giai đoạn 5: Kiểm thử, Bảo mật & Tối ưu Hiệu năng | C16: 10 | D16: =COUNTIF('WBS - 85 Tasks Backlog'!I73:I82, "✓ ĐÃ XONG") | E16: =C16-D16 | F16: =D16/C16
B17: Giai đoạn 6: Containerization, CI/CD & Go-Live | C17: 5 | D17: =COUNTIF('WBS - 85 Tasks Backlog'!I83:I87, "✓ ĐÃ XONG") | E17: =C17-D17 | F17: =D17/C17
